CHANGELOG.md
LICENSE
MANIFEST.in
README.md
requirements.txt
setup.py
start.py
octobot_node/__init__.py
octobot_node/cli.py
octobot_node/constants.py
octobot_node.egg-info/PKG-INFO
octobot_node.egg-info/SOURCES.txt
octobot_node.egg-info/dependency_links.txt
octobot_node.egg-info/entry_points.txt
octobot_node.egg-info/not-zip-safe
octobot_node.egg-info/requires.txt
octobot_node.egg-info/top_level.txt
octobot_node/app/__init__.py
octobot_node/app/enums.py
octobot_node/app/main.py
octobot_node/app/models.py
octobot_node/app/utils.py
octobot_node/app/api/__init__.py
octobot_node/app/api/deps.py
octobot_node/app/api/main.py
octobot_node/app/api/routes/__init__.py
octobot_node/app/api/routes/login.py
octobot_node/app/api/routes/nodes.py
octobot_node/app/api/routes/tasks.py
octobot_node/app/api/routes/users.py
octobot_node/app/core/__init__.py
octobot_node/app/core/config.py
octobot_node/app/core/security.py
octobot_node/scheduler/__init__.py
octobot_node/scheduler/api.py
octobot_node/scheduler/consumer.py
octobot_node/scheduler/scheduler.py
octobot_node/scheduler/task_context.py
octobot_node/scheduler/tasks.py
octobot_node/scheduler/encryption/__init__.py
octobot_node/scheduler/encryption/task_inputs.py
octobot_node/scheduler/encryption/task_outputs.py
octobot_node/ui/__init__.py
octobot_node/ui/dist/index.html
octobot_node/ui/dist/assets/card-mI_4hWDw.js
octobot_node/ui/dist/assets/index-5rRw6Pum.css
octobot_node/ui/dist/assets/index-B0m8HgN1.js
octobot_node/ui/dist/assets/loading-button-B8wzX146.js
octobot_node/ui/dist/assets/login-DlWwEXha.js
octobot_node/ui/dist/assets/system-BkYalOzS.js
octobot_node/ui/dist/assets/tasks-Cw1Lhuuv.js
octobot_node/ui/dist/assets/images/favicon.png
octobot_node/ui/dist/assets/images/octobot_node_100.png
octobot_node/ui/dist/assets/images/octobot_node_1024.png
octobot_node/ui/dist/assets/images/octobot_node_16.png
octobot_node/ui/dist/assets/images/octobot_node_256.png
octobot_node/ui/dist/assets/images/octobot_node_32.png
octobot_node/ui/dist/assets/images/octobot_node_48.png
octobot_node/ui/dist/assets/images/octobot_node_512.png
tests/app/__init__.py
tests/scheduler/__init__.py
tests/scheduler/test_api.py
tests/scheduler/test_task_context.py
tests/scheduler/task_import/__init__.py
