Metadata-Version: 2.4
Name: octobot_node
Version: 0.0.5
Summary: OctoBot Node
Home-page: https://github.com/Drakkar-Software/OctoBot-Node
Author: Drakkar-Software
Author-email: contact@drakkar.software
License: GPL-3.0
Classifier: Development Status :: 5 - Production/Stable
Classifier: Operating System :: OS Independent
Classifier: Operating System :: MacOS :: MacOS X
Classifier: Operating System :: Microsoft :: Windows
Classifier: Operating System :: POSIX
Classifier: Programming Language :: Python :: 3.10
Requires-Python: >=3.10
License-File: LICENSE
Requires-Dist: fastapi[standard]
Requires-Dist: python-multipart
Requires-Dist: passlib[bcrypt]
Requires-Dist: tenacity
Requires-Dist: pydantic
Requires-Dist: alembic
Requires-Dist: psycopg[binary]
Requires-Dist: sqlmodel
Requires-Dist: pyjwt
Requires-Dist: redis
Requires-Dist: huey
Requires-Dist: OctoBot-Commons<1.11,>=1.10
Dynamic: author
Dynamic: author-email
Dynamic: classifier
Dynamic: description
Dynamic: description-content-type
Dynamic: home-page
Dynamic: license
Dynamic: license-file
Dynamic: requires-dist
Dynamic: requires-python
Dynamic: summary
